wos_search_service/__init__.py
wos_search_service/config.py
wos_search_service/main.py
wos_search_service/modules/__init__.py
wos_search_service/modules/rest/__init__.py
wos_search_service/modules/rest/business.py
wos_search_service/modules/rest/datamodels.py
wos_search_service/modules/rest/errors.py
wos_search_service/modules/rest/schemas.py
wos_search_service/modules/rest/utils.py
wos_search_service/modules/rest/views.py
wos_search_service/utils/__init__.py
wos_search_service/utils/settings.py
wos_search_service-1.0.3.dist-info/LICENSE
wos_search_service-1.0.3.dist-info/METADATA
wos_search_service-1.0.3.dist-info/WHEEL
wos_search_service-1.0.3.dist-info/top_level.txt
wos_search_service-1.0.3.dist-info/RECORD
