Metadata-Version: 2.1
Name: wos-search-service
Version: 1.0.3
Summary: Web of Science Search Service
Home-page: https://github.com/mantis-software-company/wos-search-service
Author: Furkan Kalkan
Author-email: furkankalkan@mantis.com.tr
License: UNKNOWN
Platform: all
Classifier: License :: OSI Approved :: Apache Software License
Classifier: Topic :: Internet
Classifier: Topic :: Software Development
Classifier: Topic :: Utilities
Classifier: Intended Audience :: Developers
Classifier: Operating System :: MacOS
Classifier: Operating System :: POSIX
Classifier: Operating System :: Microsoft
Classifier: Programming Language :: Python
Classifier: Programming Language :: Python :: 3
Classifier: Programming Language :: Python :: 3.8
Requires-Python: >3.8.*, <4
Requires-Dist: Flask (~=2.0.2)
Requires-Dist: flask-smorest (~=0.35.0)
Requires-Dist: marshmallow (~=3.14.0)
Requires-Dist: pyctuator (~=0.16.0)
Requires-Dist: wos (~=0.2.5)
Requires-Dist: lxml (~=4.6.4)
Requires-Dist: python-slugify (~=5.0.2)
